{
  "Name": "Scene View",
  "Entities": [
    {
      "ID": "13987527854341289021",
      "Components": [
        {
          "ComponentType": "AquaEngine.NameComponent",
          "Name": "Scene Camera"
        },
        {
          "ComponentType": "AquaEngine.Camera",
          "FOV": 60.0,
          "Near": 0.1,
          "Far": 1000.0,
          "Orthographic": false,
          "OrthographicSize": 5.0
        },
        {
          "ComponentType": "AquaEditor.SceneViewCameraController, AquaScriptEditor, Version=0.0.0.0, Culture=neutral, PublicKeyToken=null",
          "Speed": 1.0,
          "SprintMultiplier": 2.5,
          "MouseSensitivity": {
            "x": 1.0,
            "y": 1.0
          }
        },
        {
          "ComponentType": "AquaEngine.Transform",
          "Position": {
            "x": 2.35397339,
            "y": 2.82694435,
            "z": -7.040014
          },
          "Rotation": {
            "x": 0.932017148,
            "y": -0.0831693038,
            "z": 0.351345837,
            "w": -0.03135263
          },
          "Scale": {
            "x": 1.0,
            "y": 1.0,
            "z": 1.0
          }
        }
      ]
    }
  ]
}