[
  {
    "ID": "7017954018758342678",
    "Path": "Materials/Quad.fbx/DefaultMaterial",
    "Type": "AquaEngine.Graphics.Material",
    "Properties": {
      "Shader": "0",
      "Albedo": {
        "r": 0.0,
        "g": 0.0,
        "b": 0.0,
        "a": 0.0
      },
      "AlbedoMap": "0",
      "AlphaClipping": false,
      "AlphaThreshold": 0.0
    }
  },
  {
    "ID": "9954065908068441092",
    "Path": "_Internal/PrimitiveModels/Quad",
    "Type": "AquaEngine.Graphics.Model",
    "Properties": {
      "FilePath": "assets://Models/Quad.fbx"
    }
  },
  {
    "ID": "12597370575389966382",
    "Path": "Materials/Cube.fbx/Material",
    "Type": "AquaEngine.Graphics.Material",
    "Properties": {
      "Shader": "0",
      "Albedo": {
        "r": 0.0,
        "g": 0.0,
        "b": 0.0,
        "a": 0.0
      },
      "AlbedoMap": "0",
      "AlphaClipping": false,
      "AlphaThreshold": 0.0
    }
  },
  {
    "ID": "17045091600978736333",
    "Path": "_Internal/PrimitiveModels/Cube",
    "Type": "AquaEngine.Graphics.Model",
    "Properties": {
      "FilePath": "assets://Models/Cube.fbx"
    }
  },
  {
    "ID": "3144819928286434738",
    "Path": "Materials/Sphere.fbx/DefaultMaterial",
    "Type": "AquaEngine.Graphics.Material",
    "Properties": {
      "Shader": "0",
      "Albedo": {
        "r": 0.0,
        "g": 0.0,
        "b": 0.0,
        "a": 0.0
      },
      "AlbedoMap": "0",
      "AlphaClipping": false,
      "AlphaThreshold": 0.0
    }
  },
  {
    "ID": "2522344648500585175",
    "Path": "_Internal/PrimitiveModels/Sphere",
    "Type": "AquaEngine.Graphics.Model",
    "Properties": {
      "FilePath": "assets://Models/Sphere.fbx"
    }
  },
  {
    "ID": "10121307959264177706",
    "Path": "Textures/Missing",
    "Type": "AquaEngine.Graphics.Texture",
    "Properties": {
      "FilePath": "assets://Textures/Grid.png",
      "HDR": false,
      "Filtering": 9729
    }
  },
  {
    "ID": "12740884818121143892",
    "Path": "Shaders/3D/Default",
    "Type": "AquaEngine.Graphics.Shader",
    "Properties": {
      "Vertex": "assets://Shaders/Lit.vert",
      "Fragment": "assets://Shaders/Lit.frag",
      "Compute": null,
      "Geometry": null
    }
  },
  {
    "ID": "11337244604221927022",
    "Path": "Materials/Default3D",
    "Type": "AquaEngine.Graphics.Material",
    "Properties": {
      "Shader": "12740884818121143892",
      "Albedo": {
        "r": 0.0,
        "g": 0.0,
        "b": 0.0,
        "a": 0.0
      },
      "AlbedoMap": "0",
      "AlphaClipping": false,
      "AlphaThreshold": 0.0
    }
  },
  {
    "ID": "18265258344889574232",
    "Path": "Shaders/2D/Default",
    "Type": "AquaEngine.Graphics.Shader",
    "Properties": {
      "Vertex": "assets://Shaders/Sprite.vert",
      "Fragment": "assets://Shaders/Sprite.frag",
      "Compute": null,
      "Geometry": null
    }
  },
  {
    "ID": "17452563539585698654",
    "Path": "Materials/Default2D",
    "Type": "AquaEngine.Graphics.Material",
    "Properties": {
      "Shader": "18265258344889574232",
      "Albedo": {
        "r": 0.0,
        "g": 0.0,
        "b": 0.0,
        "a": 0.0
      },
      "AlbedoMap": "0",
      "AlphaClipping": false,
      "AlphaThreshold": 0.0
    }
  },
  {
    "ID": "17947597349711903181",
    "Path": "Folder",
    "Type": "AquaEngine.Graphics.Texture",
    "Properties": {
      "FilePath": "assets://Textures/Icons/Folder.png",
      "HDR": false,
      "Filtering": 9728
    }
  },
  {
    "ID": "7900527659883124115",
    "Path": "Kenney/gear",
    "Type": "AquaEngine.Graphics.Texture",
    "Properties": {
      "FilePath": "assets://Textures/Icons/Kenney/gear.png",
      "HDR": false,
      "Filtering": 9728
    }
  },
  {
    "ID": "12940824914931632759",
    "Path": "Kenney/larger",
    "Type": "AquaEngine.Graphics.Texture",
    "Properties": {
      "FilePath": "assets://Textures/Icons/Kenney/larger.png",
      "HDR": false,
      "Filtering": 9728
    }
  },
  {
    "ID": "10273413919355332349",
    "Path": "Kenney/power",
    "Type": "AquaEngine.Graphics.Texture",
    "Properties": {
      "FilePath": "assets://Textures/Icons/Kenney/power.png",
      "HDR": false,
      "Filtering": 9728
    }
  },
  {
    "ID": "17581194969999274024",
    "Path": "Kenney/save",
    "Type": "AquaEngine.Graphics.Texture",
    "Properties": {
      "FilePath": "assets://Textures/Icons/Kenney/save.png",
      "HDR": false,
      "Filtering": 9728
    }
  },
  {
    "ID": "2806975259398877615",
    "Path": "Textures/Texture/Test_Texture09",
    "Type": "AquaEngine.Graphics.Texture",
    "Properties": {
      "FilePath": "assets://Textures/texture_09.png",
      "HDR": false,
      "Filtering": 9729
    }
  },
  {
    "ID": "6685810460470861109",
    "Path": "Shaders/NewSpriteShader",
    "Type": "AquaEngine.Graphics.Shader",
    "Properties": {
      "Vertex": "assets://Shaders/Sprite.vert",
      "Fragment": "assets://Shaders/NewSprite.frag",
      "Compute": null,
      "Geometry": null
    }
  },
  {
    "ID": "17971304626736925851",
    "Path": "project://Assets/Models/Backpack/1001_albedo.jpg",
    "Type": "AquaEngine.Graphics.Texture",
    "Properties": {
      "FilePath": "project://Assets/Models/Backpack/1001_albedo.jpg",
      "HDR": false,
      "Filtering": 9728
    }
  },
  {
    "ID": "15829790528965696159",
    "Path": "project://Assets/Models/Backpack/1001_AO.jpg",
    "Type": "AquaEngine.Graphics.Texture",
    "Properties": {
      "FilePath": "project://Assets/Models/Backpack/1001_AO.jpg",
      "HDR": false,
      "Filtering": 9728
    }
  },
  {
    "ID": "10145198931862252055",
    "Path": "project://Assets/Models/Backpack/1001_metallic.jpg",
    "Type": "AquaEngine.Graphics.Texture",
    "Properties": {
      "FilePath": "project://Assets/Models/Backpack/1001_metallic.jpg",
      "HDR": false,
      "Filtering": 9728
    }
  },
  {
    "ID": "1563596894429158729",
    "Path": "project://Assets/Models/Backpack/1001_normal.png",
    "Type": "AquaEngine.Graphics.Texture",
    "Properties": {
      "FilePath": "project://Assets/Models/Backpack/1001_normal.png",
      "HDR": false,
      "Filtering": 9728
    }
  },
  {
    "ID": "11490490004134962294",
    "Path": "project://Assets/Models/Backpack/1001_roughness.jpg",
    "Type": "AquaEngine.Graphics.Texture",
    "Properties": {
      "FilePath": "project://Assets/Models/Backpack/1001_roughness.jpg",
      "HDR": false,
      "Filtering": 9728
    }
  },
  {
    "ID": "9444867689695587868",
    "Path": "project://Assets/Textures/texture_09.png",
    "Type": "AquaEngine.Graphics.Texture",
    "Properties": {
      "FilePath": "project://Assets/Textures/texture_09.png",
      "HDR": false,
      "Filtering": 9729
    }
  }
]